README
setup.py
libfm/__init__.py
libfm.egg-info/PKG-INFO
libfm.egg-info/SOURCES.txt
libfm.egg-info/dependency_links.txt
libfm.egg-info/requires.txt
libfm.egg-info/top_level.txt