Metadata-Version: 1.0
Name: libfm
Version: 0.2
Summary: Lightweight wrapper over last.fm API
Home-page: http://github.com/MihaiDamian/Lib.fm
Author: Mihai Damian
Author-email: UNKNOWN
License: MIT License
Platform: UNKNOWN
Classifier: Development Status :: 3 - Alpha
Classifier: Intended Audience :: Developers
Classifier: License :: OSI Approved :: MIT License
Classifier: Operating System :: OS Independent
Classifier: Programming Language :: Python :: 2.5
Classifier: Topic :: Internet :: WWW/HTTP
